reportxlsxlib/__init__.py
reportxlsxlib/to_excel.py
reportxlsxlib/resources/linux/SkiaSharp.dll
reportxlsxlib/resources/linux/Spire.XLS.dll
reportxlsxlib/resources/windows/Spire.XLS.dll
reportxlsxlib-0.1.6.dist-info/METADATA
reportxlsxlib-0.1.6.dist-info/WHEEL
reportxlsxlib-0.1.6.dist-info/top_level.txt
reportxlsxlib-0.1.6.dist-info/RECORD
