Metadata-Version: 2.1
Name: reportxlsxlib
Version: 0.1.6
Summary: 这是一个操作xlsx的库,win和linux都适配
Home-page: https://github.com/bailulue
Author: bailu
Author-email: yabailu@chinatelecom.cn
License: UNKNOWN
Platform: UNKNOWN
Requires-Dist: pandas
Requires-Dist: openpyxl
Requires-Dist: pythonnet
Requires-Dist: aspose-cells (==24.5.0)
